[
	{
		"name":"godmode_users",
		"icon":"modules/user_group",
		"items":[
			{
				"name":"godmode_user_list",
				"icon":"items/user",
				"url":"/god/users/"
			},
			{
				"name":"godmode_user_groups",
				"icon":"modules/user_group",
				"url":"/god/users/groups/"
			},
			{
				"name":"godmode_user_perms",
				"icon":"items/user_perm",
				"url":"/god/users/perms/"
			}
		]
	},
	{
		"name":"godmode_simple_objects",
		"icon":"items/other",
		"items":[
			{
				"name":"godmode_static_texts",
				"icon":"items/text",
				"url":"/god/texts/"
			},
			{
				"name":"godmode_locations",
				"icon":"items/location",
				"url":"/god/locations/"
			}
		]
	}
]
